beekeeper/llms/litellm/__init__.py
beekeeper/llms/litellm/base.py
beekeeper_llms_litellm-1.0.3.dist-info/METADATA
beekeeper_llms_litellm-1.0.3.dist-info/WHEEL
beekeeper_llms_litellm-1.0.3.dist-info/RECORD
