Metadata-Version: 2.4
Name: beekeeper-llms-litellm
Version: 1.0.3
Summary: beekeeper llms litellm extension
Author-email: Leonardo Furnielis <leonardofurnielis@outlook.com>
License: Apache-2.0
Requires-Python: <3.14,>=3.11
Requires-Dist: beekeeper-core<2.0.0,>=1.0.11
Requires-Dist: litellm<2.0.0,>=1.80.10
Provides-Extra: dev
Requires-Dist: ruff>=0.14.9; extra == 'dev'
